fj/__init__.py
fj/__main__.py
fj/_cache.py
fj/_config.py
fj/_context.py
fj/_core.py
fj/_install.py
fj/_links.py
fj/_meta.py
fj/_pip.py
fj/_pool.py
fj/_subprocess.py
fj/_venv.py
fj/_zipapp.py
fj/cli.py
fj/tox_plugin.py
fj/virtualenv_plugin.py
fj/_solver/__init__.py
fj/_solver/_active.py
fj/_solver/_direct.py
fj/_solver/_distribution.py
fj/_solver/_pep503.py
fj/_solver/_pool.py
fj/_solver/_provider.py
fj/_solver/_sdist.py
fj/_solver/_source.py
fj/_solver/_wheel.py
fj/_solver/base.py
fj/_solver/parser.py
fj/_solver/solve.py
fj-0.0.4.dist-info/LICENSE.txt
fj-0.0.4.dist-info/METADATA
fj-0.0.4.dist-info/WHEEL
fj-0.0.4.dist-info/entry_points.txt
fj-0.0.4.dist-info/top_level.txt
fj-0.0.4.dist-info/RECORD
